Metadata-Version: 1.0
Name: whitenoise-player
Version: 0.0.1
Summary: White noise player
Home-page: https://python3.whitenoi.se/
Author: Adam Jenca
Author-email: jenca.a@gjh.sk
License: UNKNOWN
Platform: UNKNOWN
